{
    "library": "/home/vanessa/Desktop/Code/smeagle-examples/const/example",
    "locations": [
        {
            "function": {
                "name": "main",
                "class": "Function",
                "return": {
                    "type": "9c67aaa6ef89dd4db8543f00bd1f472f",
                    "direction": "export",
                    "location": "%rax"
                },
                "direction": "export"
            }
        }
    ],
    "types": {
        "9c67aaa6ef89dd4db8543f00bd1f472f": {
            "type": "int",
            "size": 4,
            "class": "Integer"
        }
    }
}